{
  "updated_at": 1784299847,
  "up_mid": 224267770,
  "up_name": "夏日幻听MCE",
  "count": 50,
  "videos": [
    {
      "bvid": "BV16eNR6KEQV",
      "title": "第3话『你们先走我断后，于是10年后我成为了传说』【中文字幕】",
      "link": "https://www.bilibili.com/video/BV16eNR6KEQV",
      "cover": "https://i1.hdslb.com/bfs/archive/b082a20397f4d404bc1cda048d96dae67562ee3c.jpg",
      "play": 4326,
      "created": 1784297984,
      "length": "23:40",
      "author": "夏日幻听MCE"
    },
    {
      "bvid": "BV1hQNR6XE2Z",
      "title": "【7月/正式版/真夜中】『在超市后门吸烟的二人』02【中文字幕】",
      "link": "https://www.bilibili.com/video/BV1hQNR6XE2Z",
      "cover": "https://i0.hdslb.com/bfs/archive/e9be492f9c064e2c99e6ad95aa2cdbd993f9b2c1.jpg",
      "play": 7854,
      "created": 1784294794,
      "length": "24:17",
      "author": "夏日幻听MCE"
    },
    {
      "bvid": "BV15WKj6WEQB",
      "title": "【7月】你们先走我断后，于是10年后我成为了传说 第3话预告【MCE汉化组】",
      "link": "https://www.bilibili.com/video/BV15WKj6WEQB",
      "cover": "https://i1.hdslb.com/bfs/archive/cf920191329178446268086c4de1022aefd70ed1.jpg",
      "play": 2555,
      "created": 1784294645,
      "length": "00:26",
      "author": "夏日幻听MCE"
    },
    {
      "bvid": "BV15xNd6hEqJ",
      "title": "【7月20日/续作决定】Fate/kaleid liner 魔法少女☆伊莉雅 续篇动画新情报将在7月20日公开！",
      "link": "https://www.bilibili.com/video/BV15xNd6hEqJ",
      "cover": "https://i1.hdslb.com/bfs/archive/88aa1b9a6438d02a9f57479b338d8f3e8dcdd29b.jpg",
      "play": 32063,
      "created": 1784290202,
      "length": "01:31",
      "author": "夏日幻听MCE"
    },
    {
      "bvid": "BV1SiNd69EBv",
      "title": "【7月】无职转生 第三季 第4话预告【MCE汉化组】",
      "link": "https://www.bilibili.com/video/BV1SiNd69EBv",
      "cover": "https://i0.hdslb.com/bfs/archive/dced333c220e3ca0b2c8e9449080e8ad2834701f.jpg",
      "play": 25882,
      "created": 1784283391,
      "length": "00:31",
      "author": "夏日幻听MCE"
    },
    {
      "bvid": "BV12TKn6SEyv",
      "title": "【10月】黑暗召唤师在地下恋爱中 先导PV【MCE汉化组】",
      "link": "https://www.bilibili.com/video/BV12TKn6SEyv",
      "cover": "https://i2.hdslb.com/bfs/archive/0b79d6536aedd095f80dd34d6cb6dfc2d537b2b6.jpg",
      "play": 4906,
      "created": 1784281308,
      "length": "01:05",
      "author": "夏日幻听MCE"
    },
    {
      "bvid": "BV13SKL62EGe",
      "title": "【7月18日/闽南语】葬送的芙莉莲 闽南语版 第24话预告【中文字幕】",
      "link": "https://www.bilibili.com/video/BV13SKL62EGe",
      "cover": "https://i2.hdslb.com/bfs/archive/b1867cbde477f1c0842cc920e5c0b8269c229e89.jpg",
      "play": 4234,
      "created": 1784277600,
      "length": "01:01",
      "author": "夏日幻听MCE"
    },
    {
      "bvid": "BV1vHKj69Emk",
      "title": "【7月】地狱模式～极致游戏玩家在废设定的异世界无双～第15话预告【MCE汉化组】",
      "link": "https://www.bilibili.com/video/BV1vHKj69Emk",
      "cover": "https://i1.hdslb.com/bfs/archive/47005ef0f50d857a2fd17eacfd4bc39db980283e.jpg",
      "play": 3416,
      "created": 1784273400,
      "length": "00:29",
      "author": "夏日幻听MCE"
    },
    {
      "bvid": "BV1CuKE66ESS",
      "title": "【7月】与你相恋到生命尽头 第3话预告【MCE汉化组】",
      "link": "https://www.bilibili.com/video/BV1CuKE66ESS",
      "cover": "https://i2.hdslb.com/bfs/archive/20c0c4598d58a3213362585d5160f4cc9a7b5c09.jpg",
      "play": 7763,
      "created": 1784264033,
      "length": "00:52",
      "author": "夏日幻听MCE"
    },
    {
      "bvid": "BV1cLKE6qEim",
      "title": "【10月】法国漫画改编《Dreamland》日语配音版 先导PV",
      "link": "https://www.bilibili.com/video/BV1cLKE6qEim",
      "cover": "https://i1.hdslb.com/bfs/archive/7a7e939a4d83b9fc0f2dca72e4ce03e0111dd0db.jpg",
      "play": 3636,
      "created": 1784263166,
      "length": "00:54",
      "author": "夏日幻听MCE"
    },
    {
      "bvid": "BV1cBKJ66Ew2",
      "title": "『无职转生 第三季』第4话（先行版）【中文字幕】",
      "link": "https://www.bilibili.com/video/BV1cBKJ66Ew2",
      "cover": "https://i2.hdslb.com/bfs/archive/f2d3e2558ca5928b0a6ae2693e0cb9bbfb368652.jpg",
      "play": 201634,
      "created": 1784254599,
      "length": "28:07",
      "author": "夏日幻听MCE"
    },
    {
      "bvid": "BV1vWKj6pEnK",
      "title": "【7月】我家弟弟们给你添麻烦了 第3话预告【MCE汉化组】",
      "link": "https://www.bilibili.com/video/BV1vWKj6pEnK",
      "cover": "https://i2.hdslb.com/bfs/archive/59ba1fc548897d5e761eecd063847892cc7e8924.jpg",
      "play": 2705,
      "created": 1784253600,
      "length": "00:16",
      "author": "夏日幻听MCE"
    },
    {
      "bvid": "BV13SKL62EJi",
      "title": "【4月/霸权社】小书痴的下克上 (第四季) 领主的养女 第14话预告【MCE汉化组】",
      "link": "https://www.bilibili.com/video/BV13SKL62EJi",
      "cover": "https://i1.hdslb.com/bfs/archive/e9bb314979c232cb1e1b86fec8751518f5691090.jpg",
      "play": 2978,
      "created": 1784251800,
      "length": "00:16",
      "author": "夏日幻听MCE"
    },
    {
      "bvid": "BV1q7Kj64E99",
      "title": "『尼古喵喵』03【中文字幕】",
      "link": "https://www.bilibili.com/video/BV1q7Kj64E99",
      "cover": "https://i1.hdslb.com/bfs/archive/9f29978862332a6b3a86acd41bf658ad4b642cbc.jpg",
      "play": 152365,
      "created": 1784219441,
      "length": "28:04",
      "author": "夏日幻听MCE"
    },
    {
      "bvid": "BV1AnKV6ZE99",
      "title": "『尼古喵喵』01【中文字幕】",
      "link": "https://www.bilibili.com/video/BV1AnKV6ZE99",
      "cover": "https://i1.hdslb.com/bfs/archive/fccc9a551aeed153c33ae6baa0c0b0de97cee371.jpg",
      "play": 39685,
      "created": 1784214349,
      "length": "28:07",
      "author": "夏日幻听MCE"
    },
    {
      "bvid": "BV1QyKV63EDC",
      "title": "【全14集/周更】无职转生 第三季 已更新至03【超清中字】",
      "link": "https://www.bilibili.com/video/BV1QyKV63EDC",
      "cover": "https://i1.hdslb.com/bfs/archive/e3f67660258c9df201188eb72fd8730dd4110f24.jpg",
      "play": 41316,
      "created": 1784211276,
      "length": "87:13",
      "author": "夏日幻听MCE"
    },
    {
      "bvid": "BV19WK56yEPF",
      "title": "【7月】魔法少女奈叶 EXCEEDS Gun Blaze Vengeance 第3话预告【MCE汉化组】",
      "link": "https://www.bilibili.com/video/BV19WK56yEPF",
      "cover": "https://i2.hdslb.com/bfs/archive/0555ee44d85a48aac29f778b22f1516371a81918.jpg",
      "play": 16247,
      "created": 1784207637,
      "length": "00:40",
      "author": "夏日幻听MCE"
    },
    {
      "bvid": "BV1wcKG6XEaB",
      "title": "【9月/剧场版/矢吹奈子&小野贤章】韩国动画电影《缘之信》日本上映 正式PV【MCE汉化组】",
      "link": "https://www.bilibili.com/video/BV1wcKG6XEaB",
      "cover": "https://i1.hdslb.com/bfs/archive/ccf7f881ebdc885c34f4c99314a1dedc1891c909.jpg",
      "play": 15669,
      "created": 1784194498,
      "length": "01:01",
      "author": "夏日幻听MCE"
    },
    {
      "bvid": "BV1zPNB6QEBM",
      "title": "【7月18日/闽南语】葬送的芙莉莲 闽南语版 第23话预告【中文字幕】",
      "link": "https://www.bilibili.com/video/BV1zPNB6QEBM",
      "cover": "https://i0.hdslb.com/bfs/archive/97e4390bd61ea25f9fde94416dc8e8bcc71711c9.jpg",
      "play": 4496,
      "created": 1784190600,
      "length": "00:56",
      "author": "夏日幻听MCE"
    },
    {
      "bvid": "BV1XAKV6gE7g",
      "title": "【7月】《京都幻都 -樱花幻舞-》今日上线PV【中文字幕】",
      "link": "https://www.bilibili.com/video/BV1XAKV6gE7g",
      "cover": "https://i2.hdslb.com/bfs/archive/eabdc78405f9be997de7eeea64f259da22de074c.jpg",
      "play": 6110,
      "created": 1784188350,
      "length": "00:24",
      "author": "夏日幻听MCE"
    },
    {
      "bvid": "BV1ncNB6XEEK",
      "title": "【7月】世界最强的后卫 第3话预告【MCE汉化组】",
      "link": "https://www.bilibili.com/video/BV1ncNB6XEEK",
      "cover": "https://i2.hdslb.com/bfs/archive/af7168bbda94c1fad0d4112b6c366919809c2b90.jpg",
      "play": 2898,
      "created": 1784187300,
      "length": "00:18",
      "author": "夏日幻听MCE"
    },
    {
      "bvid": "BV16ANB6pEei",
      "title": "【7月/SP/夏吉优子】尼古喵喵 迷你动画05【MCE汉化组】",
      "link": "https://www.bilibili.com/video/BV16ANB6pEei",
      "cover": "https://i1.hdslb.com/bfs/archive/80a9c76e773cd86d4a9108c2d0a9b17f3d6af633.jpg",
      "play": 88002,
      "created": 1784173800,
      "length": "00:53",
      "author": "夏日幻听MCE"
    },
    {
      "bvid": "BV1kFNB6sEEE",
      "title": "【7月/京阿尼】二十世纪电气目录 第3话预告【MCE汉化组】",
      "link": "https://www.bilibili.com/video/BV1kFNB6sEEE",
      "cover": "https://i2.hdslb.com/bfs/archive/507cfd8bd90c21664ee61986f165c51c778682ca.jpg",
      "play": 8035,
      "created": 1784171700,
      "length": "00:24",
      "author": "夏日幻听MCE"
    },
    {
      "bvid": "BV1kFNB6xEJq",
      "title": "【7月】令和的斑小姐 第3话预告【MCE汉化组】",
      "link": "https://www.bilibili.com/video/BV1kFNB6xEJq",
      "cover": "https://i2.hdslb.com/bfs/archive/9cfdcdc7b8443bbf9cc584cdb5bdb83d8024c8de.jpg",
      "play": 8863,
      "created": 1784170200,
      "length": "00:53",
      "author": "夏日幻听MCE"
    },
    {
      "bvid": "BV1rcNB69Egt",
      "title": "【7月】「我没有爱上你的打算」如此说道的下任公爵大人不知为何开始溺爱我 第3话预告【MCE汉化组】",
      "link": "https://www.bilibili.com/video/BV1rcNB69Egt",
      "cover": "https://i2.hdslb.com/bfs/archive/e977d3bc9436f34040c1e3b929c5cc06192729d3.jpg",
      "play": 4303,
      "created": 1784165400,
      "length": "00:20",
      "author": "夏日幻听MCE"
    },
    {
      "bvid": "BV1gPNz6rEk8",
      "title": "【9月/剧场版】《超时空辉夜姬》重映特别PV【MCE汉化组】",
      "link": "https://www.bilibili.com/video/BV1gPNz6rEk8",
      "cover": "https://i0.hdslb.com/bfs/archive/8324c26d46b72c331bb27ca2eb523a750d733b4c.jpg",
      "play": 61386,
      "created": 1784126308,
      "length": "01:48",
      "author": "夏日幻听MCE"
    },
    {
      "bvid": "BV1dDNi6kEwr",
      "title": "『尼古喵喵』03(先行版)【中文字幕】",
      "link": "https://www.bilibili.com/video/BV1dDNi6kEwr",
      "cover": "https://i1.hdslb.com/bfs/archive/63ac7ae242f3ef54fa62baf2479003f126b0a48f.jpg",
      "play": 818310,
      "created": 1784112337,
      "length": "28:06",
      "author": "夏日幻听MCE"
    },
    {
      "bvid": "BV1jmNi6yEoK",
      "title": "【7月19日】无职转生 第三季 04 先行图公开！",
      "link": "https://www.bilibili.com/video/BV1jmNi6yEoK",
      "cover": "https://i0.hdslb.com/bfs/archive/4406859ced4e8762991408180e9eef1096104b83.jpg",
      "play": 74048,
      "created": 1784111214,
      "length": "01:30",
      "author": "夏日幻听MCE"
    },
    {
      "bvid": "BV1TMNq6cEHw",
      "title": "【2027年1月】残月下的梅赛德斯 PV1【MCE汉化组】",
      "link": "https://www.bilibili.com/video/BV1TMNq6cEHw",
      "cover": "https://i2.hdslb.com/bfs/archive/a9482613434746261e4a246f60818ce2847435c3.jpg",
      "play": 27672,
      "created": 1784108978,
      "length": "01:01",
      "author": "夏日幻听MCE"
    },
    {
      "bvid": "BV1K3Nq6FEPk",
      "title": "【7月/夏吉优子】尼古喵喵  第3话预告【MCE汉化组】",
      "link": "https://www.bilibili.com/video/BV1K3Nq6FEPk",
      "cover": "https://i2.hdslb.com/bfs/archive/cbd5b02b3535927de7acfe1141b057eb79924e59.jpg",
      "play": 71069,
      "created": 1784107333,
      "length": "00:59",
      "author": "夏日幻听MCE"
    },
    {
      "bvid": "BV1uyNq6iEiL",
      "title": "【9月/藤本树×是枝裕和】《蓦然回首》真人电影 正式PV(中国台湾同步上映)【中文字幕】",
      "link": "https://www.bilibili.com/video/BV1uyNq6iEiL",
      "cover": "https://i0.hdslb.com/bfs/archive/dfbfe4f421737ff28535cff8f7b6bc48240465cc.jpg",
      "play": 24799,
      "created": 1784107074,
      "length": "01:04",
      "author": "夏日幻听MCE"
    },
    {
      "bvid": "BV1gUN86SE1K",
      "title": "【7月】雷霆三人行 第2话预告【MCE汉化组】",
      "link": "https://www.bilibili.com/video/BV1gUN86SE1K",
      "cover": "https://i2.hdslb.com/bfs/archive/bd8d6460ca48fb1d36fc6e08645dd5b01cfadb19.jpg",
      "play": 3687,
      "created": 1784103900,
      "length": "00:31",
      "author": "夏日幻听MCE"
    },
    {
      "bvid": "BV1nbN86YEMr",
      "title": "【7月】花样少年少女 第二季 第3话预告【中文字幕】",
      "link": "https://www.bilibili.com/video/BV1nbN86YEMr",
      "cover": "https://i2.hdslb.com/bfs/archive/02969bb4244ddc6b27d766427d4fdfbcc61df25d.jpg",
      "play": 2246,
      "created": 1784100300,
      "length": "00:16",
      "author": "夏日幻听MCE"
    },
    {
      "bvid": "BV19hNv6iEWk",
      "title": "【7月】正后方的神威 第3话预告【MCE汉化组】",
      "link": "https://www.bilibili.com/video/BV19hNv6iEWk",
      "cover": "https://i2.hdslb.com/bfs/archive/a71418f2d8cc54a542c078a052904332aeb2cdc4.jpg",
      "play": 20497,
      "created": 1784092649,
      "length": "00:35",
      "author": "夏日幻听MCE"
    },
    {
      "bvid": "BV1HxN86vERR",
      "title": "【7月】《相反的你和我》原作漫画 1-6卷 豪华特典版 已上线！",
      "link": "https://www.bilibili.com/video/BV1HxN86vERR",
      "cover": "https://i0.hdslb.com/bfs/archive/a6ae482531be66194f46781fca27b7b27ded42b4.jpg",
      "play": 3984,
      "created": 1784087400,
      "length": "01:30",
      "author": "夏日幻听MCE"
    },
    {
      "bvid": "BV1YyN86pEGG",
      "title": "【7月/彗星社】关于同一个研讨会的染谷同学是AV的这档事 第3话预告",
      "link": "https://www.bilibili.com/video/BV1YyN86pEGG",
      "cover": "https://i0.hdslb.com/bfs/archive/791483ce1fa7fc0ec1ce1298ee62125fdb12ad01.jpg",
      "play": 19365,
      "created": 1784085600,
      "length": "00:17",
      "author": "夏日幻听MCE"
    },
    {
      "bvid": "BV1xQNU68Eof",
      "title": "【7月】我独自盗墓 / 盗掘王 第2话预告【MCE汉化组】",
      "link": "https://www.bilibili.com/video/BV1xQNU68Eof",
      "cover": "https://i1.hdslb.com/bfs/archive/c9f820ec5b036c1f44ff44d95b817047e918832d.jpg",
      "play": 4825,
      "created": 1784080800,
      "length": "00:36",
      "author": "夏日幻听MCE"
    },
    {
      "bvid": "BV12QNU68EHC",
      "title": "【7月】乙女游戏世界对路人角色很不友好 第二季 第2话预告【MCE汉化组】",
      "link": "https://www.bilibili.com/video/BV12QNU68EHC",
      "cover": "https://i2.hdslb.com/bfs/archive/83bacfecc2c6091fe22d4b52460bcd760421afa5.jpg",
      "play": 3754,
      "created": 1784079000,
      "length": "00:16",
      "author": "夏日幻听MCE"
    },
    {
      "bvid": "BV1JhN86wECY",
      "title": "【7月/主题曲/ReoNa】与你相恋到生命尽头 NCOP&NCED【sajou no hana】",
      "link": "https://www.bilibili.com/video/BV1JhN86wECY",
      "cover": "https://i1.hdslb.com/bfs/archive/2458bcf96ac83075d0704428ad54c4a213ffe053.jpg",
      "play": 9874,
      "created": 1784048460,
      "length": "03:02",
      "author": "夏日幻听MCE"
    },
    {
      "bvid": "BV1T3Nt6MEko",
      "title": "【7月】与你相恋到生命尽头 02【中文字幕】",
      "link": "https://www.bilibili.com/video/BV1T3Nt6MEko",
      "cover": "https://i2.hdslb.com/bfs/archive/74a612de7dccd05675fe8394bdd3c11da485ad49.jpg",
      "play": 50930,
      "created": 1784034104,
      "length": "28:06",
      "author": "夏日幻听MCE"
    },
    {
      "bvid": "BV1tDNt66E4b",
      "title": "【8月8日/望月kei&米山舞】动画电影《缎带英雄》PV2(30s版)【中文字幕】",
      "link": "https://www.bilibili.com/video/BV1tDNt66E4b",
      "cover": "https://i1.hdslb.com/bfs/archive/793b972adcada385b84a0b014c08aae508242ca1.jpg",
      "play": 20469,
      "created": 1784032160,
      "length": "00:31",
      "author": "夏日幻听MCE"
    },
    {
      "bvid": "BV1NoNt6iEVC",
      "title": "【10月8日/剧场版/香港上映】魔法少女小圆 魔女之夜的回天 香港上映PV4【中文字幕】",
      "link": "https://www.bilibili.com/video/BV1NoNt6iEVC",
      "cover": "https://i2.hdslb.com/bfs/archive/80445c1ae57d52943b3067d5119acd4ae3ddc3f2.jpg",
      "play": 62537,
      "created": 1784027141,
      "length": "01:52",
      "author": "夏日幻听MCE"
    },
    {
      "bvid": "BV1wANb6aEca",
      "title": "【TV动画】《虎鸫》动画化决定PV【MCE汉化组】",
      "link": "https://www.bilibili.com/video/BV1wANb6aEca",
      "cover": "https://i0.hdslb.com/bfs/archive/98e513a64f8660f02d15483d900bd703bb88fea8.jpg",
      "play": 29012,
      "created": 1784026011,
      "length": "00:29",
      "author": "夏日幻听MCE"
    },
    {
      "bvid": "BV1hSNX67ELQ",
      "title": "【7月】再见，拉拉 第3话预告【MCE汉化组】",
      "link": "https://www.bilibili.com/video/BV1hSNX67ELQ",
      "cover": "https://i2.hdslb.com/bfs/archive/9026b45862f5b5b9455492eb51ad8f16bdbb312c.jpg",
      "play": 15127,
      "created": 1784020496,
      "length": "00:33",
      "author": "夏日幻听MCE"
    },
    {
      "bvid": "BV12DNU6cERE",
      "title": "【7月】荒野行动 × 伊藤润二 富江 联动PV【MCE汉化组】",
      "link": "https://www.bilibili.com/video/BV12DNU6cERE",
      "cover": "https://i2.hdslb.com/bfs/archive/9401575f518770b8508b8e31832d947e80e4a5cc.jpg",
      "play": 20212,
      "created": 1784017800,
      "length": "00:17",
      "author": "夏日幻听MCE"
    },
    {
      "bvid": "BV1FzNV6QEiL",
      "title": "【7月】Clevatess-魔兽之王与婴儿与尸之勇者- 第二季 第2话预告【MCE汉化组】",
      "link": "https://www.bilibili.com/video/BV1FzNV6QEiL",
      "cover": "https://i2.hdslb.com/bfs/archive/b784e9ed119c48a1f4da623e2fe81c952b6a3cd3.jpg",
      "play": 7772,
      "created": 1784014200,
      "length": "00:29",
      "author": "夏日幻听MCE"
    },
    {
      "bvid": "BV1YiNU66EZJ",
      "title": "【2027年1月】悠久愚者阿兹利的贤者之道 先导PV【MCE汉化组】",
      "link": "https://www.bilibili.com/video/BV1YiNU66EZJ",
      "cover": "https://i1.hdslb.com/bfs/archive/97a1b20106214eabf2ed164c57dbe6f04245ded6.jpg",
      "play": 3929,
      "created": 1783999500,
      "length": "01:31",
      "author": "夏日幻听MCE"
    },
    {
      "bvid": "BV1vYNU6kEzp",
      "title": "【7月】世界在起舞 第3话预告【MCE汉化组】",
      "link": "https://www.bilibili.com/video/BV1vYNU6kEzp",
      "cover": "https://i0.hdslb.com/bfs/archive/7a45a9c62762f842bbdca91a8e82fceed08644be.jpg",
      "play": 7605,
      "created": 1783997700,
      "length": "00:21",
      "author": "夏日幻听MCE"
    },
    {
      "bvid": "BV1WdNU6oERp",
      "title": "【7月】不虐待我的继母与继姐 第2话预告【MCE汉化组】",
      "link": "https://www.bilibili.com/video/BV1WdNU6oERp",
      "cover": "https://i2.hdslb.com/bfs/archive/6bb58dd62b7dc5501ec2c7b44679bdabcdbc4e7e.jpg",
      "play": 6625,
      "created": 1783994400,
      "length": "00:18",
      "author": "夏日幻听MCE"
    },
    {
      "bvid": "BV1HcNS6WEby",
      "title": "【7月】手牌很多的维多利亚 第2话预告【MCE汉化组】",
      "link": "https://www.bilibili.com/video/BV1HcNS6WEby",
      "cover": "https://i1.hdslb.com/bfs/archive/ce5431e0edf0a2bd948ba0abf9311f5e9f3c87fb.jpg",
      "play": 2986,
      "created": 1783992600,
      "length": "00:24",
      "author": "夏日幻听MCE"
    }
  ]
}